seehow/__init__.py
seehow/publisher.py
seehow/subscriber.py
seehowpy-0.0.1.dist-info/METADATA
seehowpy-0.0.1.dist-info/WHEEL
seehowpy-0.0.1.dist-info/top_level.txt
seehowpy-0.0.1.dist-info/RECORD
